rest_framework_api/__init__.py
rest_framework_api/apps.py
rest_framework_api/pagination.py
rest_framework_api/serializers.py
rest_framework_api/views.py
djangorestframework_api_response-0.1.0.dist-info/LICENSE
djangorestframework_api_response-0.1.0.dist-info/METADATA
djangorestframework_api_response-0.1.0.dist-info/WHEEL
djangorestframework_api_response-0.1.0.dist-info/top_level.txt
djangorestframework_api_response-0.1.0.dist-info/RECORD
