Metadata-Version: 2.1
Name: djangorestframework-api-response
Version: 0.1.0
Summary: A Django Rest Framework extension providing standardized API responses.
Home-page: https://solopython.com
Author: SoloPython
Author-email: mail@solopython.com
Maintainer: SoloPython
Maintainer-email: mail@solopython.com
License: MIT
Keywords: Django,Rest Framework,API Response,Standardized Views
Classifier: Environment :: Web Environment
Classifier: Framework :: Django
Classifier: Intended Audience :: Developers
Classifier: License :: OSI Approved :: MIT License
Classifier: Operating System :: OS Independent
Classifier: Programming Language :: Python :: 3
Classifier: Programming Language :: Python :: 3.5
Classifier: Programming Language :: Python :: 3.6
Classifier: Programming Language :: Python :: 3.7
Classifier: Programming Language :: Python :: 3.8
Classifier: Programming Language :: Python :: 3.9
Classifier: Topic :: Software Development :: Libraries :: Python Modules
License-File: LICENSE
